distribusi/__init__.py
distribusi/cli.py
distribusi/distribusi.py
distribusi/mappings.py
distribusi/page_template.py
distribusi-0.0.10.dist-info/LICENSE
distribusi-0.0.10.dist-info/METADATA
distribusi-0.0.10.dist-info/WHEEL
distribusi-0.0.10.dist-info/entry_points.txt
distribusi-0.0.10.dist-info/top_level.txt
distribusi-0.0.10.dist-info/RECORD
