Metadata-Version: 2.1
Name: distribusi
Version: 0.0.10
Summary: Distribusi is a content management system for the web that produces static pages based on the file system.
Home-page: https://git.vvvvvvaria.org/varia/distribusi
Author: Varia
License: GPLv3
Platform: any
Classifier: Programming Language :: Python :: 3
Classifier: Environment :: Console
Requires-Dist: pillow (<7.0,>=6.1.0)
Requires-Dist: python-magic (<1.0,>=0.4.15)
